AUTHORS
LICENSE
MANIFEST.in
README.rst
setup.py
django_statify.egg-info/PKG-INFO
django_statify.egg-info/SOURCES.txt
django_statify.egg-info/dependency_links.txt
django_statify.egg-info/not-zip-safe
django_statify.egg-info/requires.txt
django_statify.egg-info/top_level.txt
statify/__init__.py
statify/__init__.pyc
statify/admin.py
statify/admin.pyc
statify/context_processors.py
statify/forms.py
statify/models.py
statify/models.pyc
statify/renderers.py
statify/settings.py
statify/settings.pyc
statify/signals.py
statify/signals.pyc
statify/tests.py
statify/urls.py
statify/utils.py
statify/utils.pyc
statify/views.py
statify/locale/de/LC_MESSAGES/django.mo
statify/locale/de/LC_MESSAGES/django.po
statify/locale/en/LC_MESSAGES/django.mo
statify/locale/en/LC_MESSAGES/django.po
statify/static/statify/admin/css/statify.css
statify/static/statify/admin/img/ajax-loader.gif
statify/static/statify/admin/js/core.js
statify/static/statify/admin/js/deploy.js
statify/templates/admin/statify/release/change_form.html
statify/templates/admin/statify/release/change_list.html
statify/templates/admin/statify/release/deploy_form.html
statify/templates/admin/statify/url/change_list.html