Metadata-Version: 1.0
Name: django-statify
Version: 0.2.0
Summary: Build out a static version of your website.
Home-page: https://github.com/christian-schweinhardt/django-statify
Author: Christian Schweinhardt
Author-email: are.u.kidding@me.com
License: BSD
Download-URL: https://github.com/christian-schweinhardt/django-statify.git
Platform: UNKNOWN
Classifier: Intended Audience :: Developers
Classifier: Intended Audience :: System Administrators
Classifier: Operating System :: OS Independent
Classifier: Topic :: Software Development
Classifier: Framework :: Django
Classifier: License :: OSI Approved :: BSD License
Classifier: Environment :: Web Environment
